MANIFEST.in
README.md
setup.py
./.env
./.gitignore
./BRANCH.txt
./Dockerfile
./MANIFEST.in
./README.md
./VERSION.txt
./main_Femto.py
./main_esg.py
./main_imputation.py
./main_sparsity.py
./requirements.txt
./root_path.py
./setup.py
./.git/FETCH_HEAD
./.git/HEAD
./.git/config
./.git/description
./.git/index
./.git/hooks/applypatch-msg.sample
./.git/hooks/commit-msg.sample
./.git/hooks/fsmonitor-watchman.sample
./.git/hooks/post-update.sample
./.git/hooks/pre-applypatch.sample
./.git/hooks/pre-commit.sample
./.git/hooks/pre-merge-commit.sample
./.git/hooks/pre-push.sample
./.git/hooks/pre-rebase.sample
./.git/hooks/pre-receive.sample
./.git/hooks/prepare-commit-msg.sample
./.git/hooks/push-to-checkout.sample
./.git/hooks/update.sample
./.git/info/exclude
./.git/logs/HEAD
./.git/logs/refs/heads/master
./.git/logs/refs/remotes/origin/dev
./.git/logs/refs/remotes/origin/master
./.git/logs/refs/remotes/origin/pd.femto
./.git/logs/refs/remotes/origin/staging
./.git/objects/pack/pack-9b363512eb9596ea418a3d993ac5f6bdba6f6f4a.idx
./.git/objects/pack/pack-9b363512eb9596ea418a3d993ac5f6bdba6f6f4a.pack
./.git/refs/heads/master
./.git/refs/remotes/origin/dev
./.git/refs/remotes/origin/master
./.git/refs/remotes/origin/pd.femto
./.git/refs/remotes/origin/staging
./.git/refs/tags/v1.0
./.github/workflows/pull-request-staging.yml
./.github/workflows/pull-request.yml
./.github/workflows/push-dev.yml
./.github/workflows/push-staging.yml
./.github/workflows/push.yml
./adlinear/__init__.py
./adlinear/clusterizer.py
./adlinear/dask_tester.py
./adlinear/data_collector.py
./adlinear/features_selector.py
./adlinear/imputer.py
./adlinear/nmfmodel.py
./adlinear/ntfmodel.py
./adlinear/pca.py
./adlinear/testers.py
./adlinear/utilities.py
./adlinear.egg-info/PKG-INFO
./adlinear.egg-info/SOURCES.txt
./adlinear.egg-info/dependency_links.txt
./adlinear.egg-info/requires.txt
./adlinear.egg-info/top_level.txt
./build/lib/adlinear/__init__.py
./build/lib/adlinear/clusterizer.py
./build/lib/adlinear/dask_tester.py
./build/lib/adlinear/data_collector.py
./build/lib/adlinear/features_selector.py
./build/lib/adlinear/imputer.py
./build/lib/adlinear/nmfmodel.py
adlinear.egg-info/PKG-INFO
adlinear.egg-info/SOURCES.txt
adlinear.egg-info/dependency_links.txt
adlinear.egg-info/requires.txt
adlinear.egg-info/top_level.txt
